ngofile/__init__.py
ngofile/__main__.py
ngofile/cli.py
ngofile/copy.py
ngofile/exceptions.py
ngofile/list_files.py
ngofile/pathlist.py
ngofile/__pycache__/__init__.cpython-36 (conflicted copy 2019-11-22 162128).pyc
ngofile/__pycache__/__init__.cpython-36.pyc
ngofile/__pycache__/__init__.cpython-37.pyc
ngofile/__pycache__/exceptions.cpython-36 (conflicted copy 2019-11-22 162128).pyc
ngofile/__pycache__/exceptions.cpython-36.pyc
ngofile/__pycache__/exceptions.cpython-37.pyc
ngofile/__pycache__/list_files.cpython-36 (conflicted copy 2020-04-08 104020).pyc
ngofile/__pycache__/list_files.cpython-36.pyc
ngofile/__pycache__/list_files.cpython-37.pyc
ngofile/__pycache__/pathlist.cpython-36 (conflicted copy 2020-05-20 055126).pyc
ngofile/__pycache__/pathlist.cpython-36.pyc
ngofile/__pycache__/pathlist.cpython-37.pyc
ngofile/s3/__init__.py
ngofile/s3/download.py
ngofile/s3/progress_bar.py
ngofile/s3/upload.py
ngofile/s3/utils.py
ngofile-1.0.1.dist-info/AUTHORS.rst
ngofile-1.0.1.dist-info/LICENSE
ngofile-1.0.1.dist-info/METADATA
ngofile-1.0.1.dist-info/WHEEL
ngofile-1.0.1.dist-info/entry_points.txt
ngofile-1.0.1.dist-info/top_level.txt
ngofile-1.0.1.dist-info/RECORD
