Metadata-Version: 2.1
Name: ngofile
Version: 1.0.1
Summary: misc file utilities
Home-page: https://github.com/numengo/python-ngofile2
Author: Cédric ROMAN
Author-email: roman@numengo.com
License: GNU General Public License v3
Keywords: utilities
Platform: UNKNOWN
Classifier: Development Status :: 3 - Alpha
Classifier: Intended Audience :: Developers
Classifier: License :: OSI Approved :: GNU General Public License v3 (GPLv3)
Classifier: Operating System :: Unix
Classifier: Operating System :: POSIX
Classifier: Operating System :: Microsoft :: Windows
Classifier: Programming Language :: Python
Classifier: Programming Language :: Python :: 2.7
Classifier: Programming Language :: Python :: 3.7
Classifier: Programming Language :: Python :: 3.8
Classifier: Programming Language :: Python :: 3.9
Classifier: Programming Language :: Python :: 3.10
Classifier: Programming Language :: Python :: 3.11
Classifier: Programming Language :: Python :: 2
Classifier: Programming Language :: Python :: 3
Classifier: Programming Language :: Python :: Implementation :: CPython
Classifier: Topic :: Utilities
License-File: LICENSE
License-File: AUTHORS.rst
Requires-Dist: future
Requires-Dist: python-gettext
Requires-Dist: python-dateutil
Requires-Dist: click
Requires-Dist: pathlib
Requires-Dist: boto
